{
	"id": "5bd1ffe1-2c98-4b1c-8473-5d9319d1b484",
	"name": "Akamai | Live Video Workflow as Code",
	"values": [
		{
			"key": "host",
			"value": "",
			"enabled": true
		},
		{
			"key": "client_token",
			"value": "",
			"enabled": true
		},
		{
			"key": "client_secret",
			"value": "",
			"enabled": true
		},
		{
			"key": "access_token",
			"value": "",
			"enabled": true
		},
		{
			"key": "contractId",
			"value": "",
			"enabled": true
		},
		{
			"key": "cpCodeName_MSL",
			"value": "",
			"enabled": true
		},
		{
			"key": "cpCode_MSL",
			"value": "",
			"enabled": true
		},
		{
			"key": "hostnameIdentifier",
			"value": "",
			"enabled": true
		},
		{
			"key": "encoderZone",
			"value": "",
			"enabled": true
		},
		{
			"key": "backupEncoderZone",
			"value": "",
			"enabled": true
		},
		{
			"key": "hostname_MSL",
			"value": "",
			"enabled": true
		},
		{
			"key": "streamName",
			"value": "",
			"enabled": true
		},
		{
			"key": "streamingFormat",
			"value": "",
			"enabled": true
		},
		{
			"key": "streamId",
			"value": "",
			"enabled": true
		},
		{
			"key": "publishingUrl",
			"value": "",
			"enabled": true
		},
		{
			"key": "groupId",
			"value": "",
			"enabled": true
		},
		{
			"key": "cpCodeName_AMD",
			"value": "",
			"enabled": true
		},
		{
			"key": "cpCode_AMD",
			"value": "",
			"enabled": true
		},
		{
			"key": "propertyName",
			"value": "",
			"enabled": true
		},
		{
			"key": "propertyHostname",
			"value": "",
			"enabled": true
		},
		{
			"key": "propertyVersion",
			"value": "",
			"enabled": true
		},
		{
			"key": "propertyId",
			"value": "",
			"enabled": true
		},
		{
			"key": "activationEmail",
			"value": "",
			"enabled": true
		},
		{
			"key": "activationNote",
			"value": "",
			"enabled": true
		},
		{
			"key": "network",
			"value": "",
			"enabled": true
		}
	],
	"_postman_variable_scope": "environment",
	"_postman_exported_at": "2020-09-29T13:47:57.597Z",
	"_postman_exported_using": "Postman/7.33.1"
}